celery_task_locker/__init__.py
celery_task_locker/task_locker.py
celery_task_locker-0.1.3.dist-info/DESCRIPTION.rst
celery_task_locker-0.1.3.dist-info/METADATA
celery_task_locker-0.1.3.dist-info/RECORD
celery_task_locker-0.1.3.dist-info/WHEEL
celery_task_locker-0.1.3.dist-info/metadata.json
celery_task_locker-0.1.3.dist-info/top_level.txt
