Metadata-Version: 2.0
Name: celery-task-locker
Version: 0.1.3
Summary: Ensuring a task is only executed one at a time
Home-page: https://github.com/maxtwen/celery-task-locker
Author: maxtwen
Author-email: maxtwen@yandex.ru
License: MIT
Platform: UNKNOWN
Requires-Dist: celery (>=3.1.23)
Requires-Dist: redis (>=2.10.5)
